gft/__init__.py
gft/gft_cat_data.py
gft/gft_eval.py
gft/gft_fit.py
gft/gft_predict.py
gft/gft_summary.py
gft/gft_internals/__init__.py
gft/gft_internals/eval_for_classify.py
gft/gft_internals/eval_for_classify_classic.py
gft/gft_internals/eval_for_classify_hf.py
gft/gft_internals/eval_for_classify_pd.py
gft/gft_internals/eval_for_classify_spans.py
gft/gft_internals/eval_for_classify_spans_hf.py
gft/gft_internals/eval_for_classify_spans_pd.py
gft/gft_internals/eval_for_classify_tokens.py
gft/gft_internals/eval_for_ctc.py
gft/gft_internals/eval_for_regress.py
gft/gft_internals/eval_for_regress_hf.py
gft/gft_internals/eval_for_regress_pd.py
gft/gft_internals/fit_for_classify.py
gft/gft_internals/fit_for_classify_classic.py
gft/gft_internals/fit_for_classify_hf.py
gft/gft_internals/fit_for_classify_pd.py
gft/gft_internals/fit_for_classify_spans.py
gft/gft_internals/fit_for_classify_spans_hf.py
gft/gft_internals/fit_for_classify_spans_pd.py
gft/gft_internals/fit_for_classify_tokens.py
gft/gft_internals/fit_for_ctc.py
gft/gft_internals/fit_for_regress.py
gft/gft_internals/fit_for_regress_hf.py
gft/gft_internals/fit_for_regress_pd.py
gft/gft_internals/gft_predict_hf.py
gft/gft_internals/gft_predict_pd.py
gft/gft_internals/gft_summary_hf.py
gft/gft_internals/gft_summary_pd.py
gft/gft_internals/gft_util.py
gft/gft_internals/loadable_models.py
gft/gft_internals/my_auto_model_hf.py
gft/gft_internals/my_auto_model_pd.py
gft/gft_internals/my_auto_model_util.py
gft/gft_internals/my_datasets.py
gft/gft_internals/my_task.py
gft/gft_internals/paddle_dataset_zoo.py
gft/gft_internals/paddle_model_zoo.py
gft/gft_internals/parse_args.py
gft/gft_internals/parse_eqn.py
gft/gft_internals/predict_speech.py
gft/gft_internals/run_qa.py
gft/gft_internals/trainer_qa.py
gft/gft_internals/utils_qa.py
gft/gft_internals/huggingface_hub/__init__.py
gft/gft_internals/huggingface_hub/has_tokenizer.py
gft/gft_internals/huggingface_hub/list_adapters.py
gft-0.1.4.dist-info/LICENSE
gft-0.1.4.dist-info/METADATA
gft-0.1.4.dist-info/WHEEL
gft-0.1.4.dist-info/entry_points.txt
gft-0.1.4.dist-info/top_level.txt
gft-0.1.4.dist-info/RECORD
