Metadata-Version: 2.1
Name: gft
Version: 0.1.4
Summary: GFT (general fine-tuning) A Little Language for Deepnets: 1-line programs for fine-tuning, inference and more
Home-page: https://github.com/kwchurch/gft
Author: GFT Authors
Author-email: kenneth.ward.church@gmail.com
License: Apache 2.0
Platform: UNKNOWN
Classifier: Programming Language :: Python :: 3
Classifier: Programming Language :: Python :: 3.6
Classifier: Programming Language :: Python :: 3.7
Classifier: Programming Language :: Python :: 3.8
Classifier: License :: OSI Approved :: Apache Software License
Classifier: Operating System :: OS Independent
Requires-Python: >=3.6
Requires-Dist: LAC
Requires-Dist: accelerate
Requires-Dist: apache-beam
Requires-Dist: argparse
Requires-Dist: conllu
Requires-Dist: datasets
Requires-Dist: ftfy
Requires-Dist: huggingface-hub
Requires-Dist: importlib-metadata
Requires-Dist: jiwer
Requires-Dist: librosa
Requires-Dist: matplotlib
Requires-Dist: multiprocess (==0.70.8)
Requires-Dist: numpy
Requires-Dist: paddlehub
Requires-Dist: paddlenlp
Requires-Dist: paddlepaddle-gpu
Requires-Dist: py7zr
Requires-Dist: pypinyin
Requires-Dist: requests
Requires-Dist: scipy
Requires-Dist: sentencepiece
Requires-Dist: seqeval
Requires-Dist: sklearn
Requires-Dist: soundfile
Requires-Dist: spacy
Requires-Dist: timm
Requires-Dist: tokenizers
Requires-Dist: torch
Requires-Dist: torchaudio
Requires-Dist: tqdm
Requires-Dist: transformers
Requires-Dist: typing
Requires-Dist: wheel
Requires-Dist: yacs
